dewildcard.py
python_dewildcard-0.2.2.dist-info/DESCRIPTION.rst
python_dewildcard-0.2.2.dist-info/METADATA
python_dewildcard-0.2.2.dist-info/RECORD
python_dewildcard-0.2.2.dist-info/WHEEL
python_dewildcard-0.2.2.dist-info/entry_points.txt
python_dewildcard-0.2.2.dist-info/metadata.json
python_dewildcard-0.2.2.dist-info/top_level.txt
