Metadata-Version: 2.0
Name: python-dewildcard
Version: 0.2.2
Summary: Expand wildcard imports in Python code
Home-page: http://github.com/quentinsf/dewildcard
Author: Quentin Stafford-Fraser
Author-email: quentin@pobox.com
License: UNKNOWN
Download-URL: https://github.com/quentinsf/dewildcard/tarball/0.1
Keywords: pylint
Platform: UNKNOWN
